simple_message/__init__.py
simple_message/simple_message.py
simple_message-0.0.1a9.dist-info/LICENSE
simple_message-0.0.1a9.dist-info/METADATA
simple_message-0.0.1a9.dist-info/WHEEL
simple_message-0.0.1a9.dist-info/top_level.txt
simple_message-0.0.1a9.dist-info/RECORD
