Metadata-Version: 2.1
Name: simple-message
Version: 0.0.1a9
Summary: A package for sending basic Slack messages with minimal coding
Home-page: https://github.com/billsanto/simple_message
Author: William Santo
Author-email: author@example.com
License: UNKNOWN
Project-URL: Bug Tracker, https://github.com/billsanto/simple_message/issues
Platform: UNKNOWN
Classifier: Programming Language :: Python :: 3
Classifier: License :: OSI Approved :: MIT License
Classifier: Operating System :: OS Independent
Requires-Python: >=3.6
License-File: LICENSE
Requires-Dist: slack-sdk (>=3.10)
